wrong_answer/__init__.py
wrong_answer/main.py
wrong_answer-0.0.10.dist-info/LICENSE
wrong_answer-0.0.10.dist-info/METADATA
wrong_answer-0.0.10.dist-info/WHEEL
wrong_answer-0.0.10.dist-info/entry_points.txt
wrong_answer-0.0.10.dist-info/top_level.txt
wrong_answer-0.0.10.dist-info/RECORD
