Metadata-Version: 2.1
Name: wrong-answer
Version: 0.0.10
Summary: Download AtCoder Testcases
Home-page: https://github.com/takoha-cpp/WrongAnswer
Author: Takoha
Author-email: author@example.com
License: UNKNOWN
Project-URL: Documentation, https://takoha-cpp.github.io/WrongAnswer
Project-URL: Source, https://github.com/takoha-cpp/WrongAnswer
Keywords: downloader competitive-programming AtCoder test-cases
Platform: UNKNOWN
Classifier: Programming Language :: Python :: 3
Classifier: License :: OSI Approved :: Apache Software License
Classifier: Operating System :: OS Independent
Classifier: Development Status :: 3 - Alpha
Requires-Python: >=3.6
Requires-Dist: online-judge-tools (>=11.0.0)
